LICENSE
MANIFEST.in
README.rst
VERSION
requirements.txt
setup.cfg
setup.py
consular/__init__.py
consular/__init__.pyc
consular/cli.py
consular/cli.pyc
consular/clients.py
consular/clients.pyc
consular/main.py
consular/main.pyc
consular.egg-info/PKG-INFO
consular.egg-info/SOURCES.txt
consular.egg-info/dependency_links.txt
consular.egg-info/entry_points.txt
consular.egg-info/not-zip-safe
consular.egg-info/requires.txt
consular.egg-info/top_level.txt
consular/tests/__init__.py
consular/tests/__init__.pyc
consular/tests/test_clients.py
consular/tests/test_main.py
consular/tests/__pycache__/test_clients.cpython-27-PYTEST.pyc
consular/tests/__pycache__/test_main.cpython-27-PYTEST.pyc