Metadata-Version: 1.1
Name: consular
Version: 1.3.0
Summary: Consular
Home-page: http://github.com/universalcore/consular
Author: Simon de Haan
Author-email: simon@praekeltfoundation.org
License: BSD
Keywords: marathon,consul,mesos
Platform: UNKNOWN
Classifier: Programming Language :: Python
Classifier: Topic :: Internet :: WWW/HTTP
Classifier: Topic :: Internet :: WWW/HTTP :: WSGI :: Application
